pipython/PILogger.py
pipython/__init__.py
pipython/version.py
pipython/datarectools/__init__.py
pipython/datarectools/datarectools.py
pipython/fastaligntools/__init__.py
pipython/fastaligntools/fastaligntools.py
pipython/gcscommands/__init__.py
pipython/gcserror/__init__.py
pipython/gcsmessages/__init__.py
pipython/interfaces/__init__.py
pipython/interfaces/gcsdll/__init__.py
pipython/interfaces/pigateway/__init__.py
pipython/interfaces/piserial/__init__.py
pipython/interfaces/pisocket/__init__.py
pipython/interfaces/piusb/__init__.py
pipython/pidevice/__init__.py
pipython/pidevice/gcscommands.py
pipython/pidevice/gcsdevice.py
pipython/pidevice/gcserror.py
pipython/pidevice/gcsmessages.py
pipython/pidevice/pierror_base.py
pipython/pidevice/piparams.py
pipython/pidevice/common/__init__.py
pipython/pidevice/common/gcsbasecommands.py
pipython/pidevice/common/gcsbasedatarectools.py
pipython/pidevice/common/gcsbasedevice.py
pipython/pidevice/common/gcscommands_helpers.py
pipython/pidevice/gcs2/__init__.py
pipython/pidevice/gcs2/gcs2commands.py
pipython/pidevice/gcs2/gcs2datarectools.py
pipython/pidevice/gcs2/gcs2device.py
pipython/pidevice/gcs2/gcs2fastaligntools.py
pipython/pidevice/gcs30/CustomError.json
pipython/pidevice/gcs30/__init__.py
pipython/pidevice/gcs30/gcs30commands.py
pipython/pidevice/gcs30/gcs30commands_helpers.py
pipython/pidevice/gcs30/gcs30datarectools.py
pipython/pidevice/gcs30/gcs30device.py
pipython/pidevice/gcs30/gcs30error.py
pipython/pidevice/interfaces/__init__.py
pipython/pidevice/interfaces/gcsdll.py
pipython/pidevice/interfaces/pigateway.py
pipython/pidevice/interfaces/piserial.py
pipython/pidevice/interfaces/pisocket.py
pipython/pidevice/interfaces/piusb.py
pipython/piparams/__init__.py
pipython/pitools/__init__.py
pipython/pitools/pitools.py
pipython/pitools/replyserver.py
pipython/pitools/common/__init__.py
pipython/pitools/common/gcsbasepitools.py
pipython/pitools/gcs2/__init__.py
pipython/pitools/gcs2/gcs2pitools.py
PIPython-2.10.2.1.dist-info/METADATA
PIPython-2.10.2.1.dist-info/WHEEL
PIPython-2.10.2.1.dist-info/eula.md
PIPython-2.10.2.1.dist-info/top_level.txt
PIPython-2.10.2.1.dist-info/RECORD
