Metadata-Version: 2.1
Name: PIPython
Version: 2.10.2.1
Summary: Collection of libraries to use PI devices and process GCS data.
Home-page: http://www.physikinstrumente.com
Author: Physik Instrumente (PI) GmbH & Co. KG
Author-email: service@pi.de
Keywords: PI,PIPython,physikinstrumente,Physik Instrumente,GCS
Classifier: Development Status :: 5 - Production/Stable
Classifier: License :: Other/Proprietary License
Classifier: Programming Language :: Python :: 3
Classifier: Programming Language :: Python :: 3.6
Requires-Python: >=3.6
License-File: eula.md
Requires-Dist: pyusb
Requires-Dist: pyserial
